cc_sessions/__init__.py
cc_sessions/install.py
cc_sessions/agents/code-review.md
cc_sessions/agents/context-gathering.md
cc_sessions/agents/context-refinement.md
cc_sessions/agents/logging.md
cc_sessions/agents/service-documentation.md
cc_sessions/commands/sessions.md
cc_sessions/knowledge/claude-code/hooks-reference.md
cc_sessions/knowledge/claude-code/project-directory-references.md
cc_sessions/knowledge/claude-code/slash-commands.md
cc_sessions/knowledge/claude-code/subagents.md
cc_sessions/knowledge/claude-code/tool-permissions.md
cc_sessions/protocols/context-compaction/context-compaction.md
cc_sessions/protocols/kickstart/01-agents-only.md
cc_sessions/protocols/kickstart/01-discussion.md
cc_sessions/protocols/kickstart/02-implementation.md
cc_sessions/protocols/kickstart/03-tasks-overview.md
cc_sessions/protocols/kickstart/04-task-creation.md
cc_sessions/protocols/kickstart/05-task-startup.md
cc_sessions/protocols/kickstart/06-task-completion.md
cc_sessions/protocols/kickstart/07-compaction.md
cc_sessions/protocols/kickstart/08-agents.md
cc_sessions/protocols/kickstart/09-api.md
cc_sessions/protocols/kickstart/10-advanced.md
cc_sessions/protocols/kickstart/11-graduation.md
cc_sessions/protocols/task-completion/commit-standard.md
cc_sessions/protocols/task-completion/commit-style-conventional.md
cc_sessions/protocols/task-completion/commit-style-detailed.md
cc_sessions/protocols/task-completion/commit-style-simple.md
cc_sessions/protocols/task-completion/commit-superrepo.md
cc_sessions/protocols/task-completion/directory-task-completion.md
cc_sessions/protocols/task-completion/git-add-warning.md
cc_sessions/protocols/task-completion/staging-all.md
cc_sessions/protocols/task-completion/staging-ask.md
cc_sessions/protocols/task-completion/subtask-completion.md
cc_sessions/protocols/task-completion/task-completion.md
cc_sessions/protocols/task-creation/task-creation.md
cc_sessions/protocols/task-startup/directory-task-startup.md
cc_sessions-0.3.6.dist-info/licenses/LICENSE
cc_sessions-0.3.6.dist-info/METADATA
cc_sessions-0.3.6.dist-info/WHEEL
cc_sessions-0.3.6.dist-info/entry_points.txt
cc_sessions-0.3.6.dist-info/top_level.txt
cc_sessions-0.3.6.dist-info/RECORD
